x100http
tests/sta
tests
