Metadata-Version: 1.1
Name: x100http
Version: 0.2.6
Summary: web framework support customing file upload processing
Home-page: https://github.com/chengang/x100http
Author: Chen Gang
Author-email: yikuyiku.com@gmail.com
License: MIT
Keywords: http framework webframework file upload rfc1867 x100
Platform: UNKNOWN
Classifier: Development Status :: 5 - Production/Stable
Classifier: Intended Audience :: Developers
Classifier: Topic :: Internet :: WWW/HTTP :: HTTP Servers
Classifier: Topic :: Multimedia :: Video :: Conversion
Classifier: License :: OSI Approved :: MIT License
Classifier: Programming Language :: Python :: 3.4
Classifier: Programming Language :: Python :: 3 :: Only
